filelister/.pylintrc
filelister/DataStorage.py
filelister/Filelist.py
filelister/__init__.py
filelister/read_filelist.py
filelister-0.0.1.dist-info/LICENSE
filelister-0.0.1.dist-info/WHEEL
filelister-0.0.1.dist-info/METADATA
filelister-0.0.1.dist-info/RECORD
