Metadata-Version: 2.1
Name: filelister
Version: 0.0.1
Summary: Filelister is a Python package that makes working with filelists (yes, lists of files) easy.
Author: NaN Developers
Author-email: nanwtf@proton.me
Requires-Python: >=3.8,<4.0
Classifier: Programming Language :: Python :: 3
Classifier: Programming Language :: Python :: 3.8
Classifier: Programming Language :: Python :: 3.9
Classifier: Programming Language :: Python :: 3.10
Requires-Dist: termcolor (>=1.1.0,<2.0.0)
